toml_sort/__init__.py
toml_sort/cli.py
toml_sort/py.typed
toml_sort/tomlsort.py
toml_sort-0.24.3.dist-info/LICENSE
toml_sort-0.24.3.dist-info/METADATA
toml_sort-0.24.3.dist-info/WHEEL
toml_sort-0.24.3.dist-info/entry_points.txt
toml_sort-0.24.3.dist-info/RECORD
