Metadata-Version: 2.3
Name: toml-sort
Version: 0.24.3
Summary: Toml sorting library
License: MIT
Keywords: toml,sort,cli,unix,utility
Author: Sam Roeca
Author-email: samuel.roeca@gmail.com
Requires-Python: >=3.9
Classifier: Development Status :: 4 - Beta
Classifier: Environment :: Console
Classifier: License :: OSI Approved :: MIT License
Classifier: Programming Language :: Python :: 3
Classifier: Programming Language :: Python :: 3.9
Classifier: Programming Language :: Python :: 3.10
Classifier: Programming Language :: Python :: 3.11
Classifier: Programming Language :: Python :: 3.12
Classifier: Programming Language :: Python :: 3.13
Classifier: Topic :: Software Development :: Code Generators
Classifier: Topic :: Utilities
Classifier: Typing :: Typed
Requires-Dist: tomlkit (>=0.13.2)
Project-URL: Homepage, https://github.com/pappasam/toml-sort
Project-URL: Repository, https://github.com/pappasam/toml-sort
